requirements_txt/__init__.py
requirements_txt/__main__.py
requirements_txt/commands/__init__.py
requirements_txt/commands/cli.py
requirements_txt/commands/config/__init__.py
requirements_txt/commands/config/command.py
requirements_txt/commands/config/service.py
requirements_txt/commands/init/__init__.py
requirements_txt/commands/init/command.py
requirements_txt/commands/init/service.py
requirements_txt/commands/install/__init__.py
requirements_txt/commands/install/command.py
requirements_txt/commands/install/service.py
requirements_txt/commands/show/__init__.py
requirements_txt/commands/show/command.py
requirements_txt/commands/show/service.py
requirements_txt/static/__init__.py
requirements_txt/static/new_pip.py
requirements_txt/utils/__init__.py
requirements_txt/utils/appdata.py
requirements_txt/utils/check.py
requirements_txt/utils/config.py
requirements_txt/utils/consts.py
requirements_txt/utils/crossplatform.py
requirements_txt/utils/logging.py
requirements_txt/utils/override.py
requirements_txt/utils/path.py
requirements_txt/utils/pip/__init__.py
requirements_txt/utils/pip/parsers.py
requirements_txt/utils/pip/restrictions.py
requirements_txt/utils/pip/service.py
tests/__init__.py
tests/integrationtests/__init__.py
tests/integrationtests/test_pip.py
tests/integrationtests/test_commands/__init__.py
tests/integrationtests/test_commands/test_config/__init__.py
tests/integrationtests/test_commands/test_config/test_command.py
tests/integrationtests/test_commands/test_init/__init__.py
tests/integrationtests/test_commands/test_init/conftest.py
tests/integrationtests/test_commands/test_init/test_command.py
tests/integrationtests/test_commands/test_install/__init__.py
tests/integrationtests/test_commands/test_install/conftest.py
tests/integrationtests/test_commands/test_install/test_command.py
tests/integrationtests/test_commands/test_show/__init__.py
tests/integrationtests/test_commands/test_show/test_command.py
tests/unittests/__init__.py
toreqs-2.0.14.dist-info/licenses/LICENSE.md
toreqs-2.0.14.dist-info/METADATA
toreqs-2.0.14.dist-info/WHEEL
toreqs-2.0.14.dist-info/entry_points.txt
toreqs-2.0.14.dist-info/top_level.txt
toreqs-2.0.14.dist-info/RECORD
